fortio.py
fortio-0.4.dist-info/LICENSE
fortio-0.4.dist-info/METADATA
fortio-0.4.dist-info/WHEEL
fortio-0.4.dist-info/top_level.txt
fortio-0.4.dist-info/RECORD
