Metadata-Version: 2.1
Name: fortio
Version: 0.4
Summary: A Python IO for Fortran unformatted binary files with variable-length records.
Home-page: https://github.com/syrte/fortio/
Author: Syrtis Major
Author-email: styr.py@gmail.com
License: UNKNOWN
Keywords: Fortran,Numpy
Platform: UNKNOWN
Classifier: Development Status :: 5 - Production/Stable
Classifier: Topic :: Scientific/Engineering
Classifier: License :: OSI Approved :: GNU General Public License v2 (GPLv2)
Classifier: Programming Language :: Python :: 2
Classifier: Programming Language :: Python :: 3
